pickleslicer/__init__.py
pickleslicer/pickle_slicer.py
pickleslicer-0.1.0.dist-info/LICENSE
pickleslicer-0.1.0.dist-info/METADATA
pickleslicer-0.1.0.dist-info/WHEEL
pickleslicer-0.1.0.dist-info/top_level.txt
pickleslicer-0.1.0.dist-info/RECORD
