Metadata-Version: 2.1
Name: pickleslicer
Version: 0.1.0
Summary: Automatic slicer and unslicer of pickle files.
Home-page: https://github.com/rmshaffer/pickle-slicer
Author: Ryan Shaffer
Author-email: ryan@ryanshaffer.net
License: UNKNOWN
Platform: UNKNOWN
Classifier: Programming Language :: Python :: 3
Classifier: License :: OSI Approved :: MIT License
Classifier: Operating System :: OS Independent
Requires-Python: >=3.6
